Metadata-Version: 1.0
Name: gaussian-binomial-distributions-FT
Version: 0.1
Summary: gaussian_binomial_distributions
Home-page: UNKNOWN
Author: Funing Tian
Author-email: UNKNOWN
License: UNKNOWN
Platform: UNKNOWN
